in_n_out_clients/__init__.py
in_n_out_clients/bigquery_client.py
in_n_out_clients/config.py
in_n_out_clients/email_client.py
in_n_out_clients/google_calendar_client.py
in_n_out_clients/google_drive_client.py
in_n_out_clients/in_n_out_types.py
in_n_out_clients/main.py
in_n_out_clients/postgres_client.py
in_n_out_clients-0.5.0.dist-info/LICENSE
in_n_out_clients-0.5.0.dist-info/METADATA
in_n_out_clients-0.5.0.dist-info/WHEEL
in_n_out_clients-0.5.0.dist-info/top_level.txt
in_n_out_clients-0.5.0.dist-info/RECORD
