Metadata-Version: 2.1
Name: in-n-out-clients
Version: 0.5.0
Summary: Clients for In-N-Out
Home-page: https://github.com/namiyousef/in-n-out-clients
Author: Yousef Nami
Author-email: namiyousef@hotmail.com
License: MIT
License-File: LICENSE
Requires-Dist: google-api-python-client
Requires-Dist: google-auth-httplib2
Requires-Dist: google-auth-oauthlib
Requires-Dist: psycopg2-binary
Requires-Dist: PyDrive2
Requires-Dist: pandas
Requires-Dist: SQLAlchemy
Provides-Extra: test
Requires-Dist: pre-commit ; extra == 'test'
Requires-Dist: pytest ; extra == 'test'
Requires-Dist: coverage ; extra == 'test'
